convertjson1/__init__.py
convertjson1/convertjson1.py
convertjson1-1.0.2.dist-info/LICENSE
convertjson1-1.0.2.dist-info/METADATA
convertjson1-1.0.2.dist-info/WHEEL
convertjson1-1.0.2.dist-info/top_level.txt
convertjson1-1.0.2.dist-info/RECORD
