Metadata-Version: 2.1
Name: convertjson1
Version: 1.0.2
Summary: Json to tree Hierarchy converter
Author: PavanPawar
Author-email: pppawar124@gmail.com
Keywords: json,graph,nodeId,child,name
Classifier: License :: OSI Approved :: MIT License
Classifier: Development Status :: 1 - Planning
Classifier: Intended Audience :: Developers
Classifier: Programming Language :: Python :: 3
Classifier: Operating System :: OS Independent
Requires-Python: >=3.11
License-File: LICENSE
